tnia/__init__.py
tnia/__pycache__/__init__.cpython-310.pyc
tnia/__pycache__/__init__.cpython-311.pyc
tnia/__pycache__/__init__.cpython-312.pyc
tnia/__pycache__/__init__.cpython-39.pyc
tnia/alignment/__init__.py
tnia/alignment/simpleelastix.py
tnia/background/__init__.py
tnia/background/dilate_subtract.py
tnia/background/helper.py
tnia/background/rolling_ball.py
tnia/background/__pycache__/__init__.cpython-310.pyc
tnia/background/__pycache__/rolling_ball.cpython-310.pyc
tnia/deconvolution/__init__.py
tnia/deconvolution/decon_helper.py
tnia/deconvolution/fftdeconv.py
tnia/deconvolution/forward.py
tnia/deconvolution/gaussian_psf.py
tnia/deconvolution/pad.py
tnia/deconvolution/psfs.py
tnia/deconvolution/richardson_lucy.py
tnia/deconvolution/richardson_lucy_dask_cp.py
tnia/deconvolution/richardson_lucy_gradient_consensus.py
tnia/deconvolution/richardson_lucy_gradient_consensus_2025_06_22.py
tnia/deconvolution/richardson_lucy_gradient_consensus_biggs.py
tnia/deconvolution/richardson_lucy_gradient_consensus_latest.py
tnia/deconvolution/richardson_lucy_gradient_consensus_latest_sandbox.py
tnia/deconvolution/richardson_lucy_np.py
tnia/deconvolution/richardson_lucy_poisson_thinning.py
tnia/deconvolution/richardson_lucy_variable.py
tnia/deconvolution/__pycache__/__init__.cpython-310.pyc
tnia/deconvolution/__pycache__/__init__.cpython-312.pyc
tnia/deconvolution/__pycache__/__init__.cpython-39.pyc
tnia/deconvolution/__pycache__/decon_helper.cpython-312.pyc
tnia/deconvolution/__pycache__/forward.cpython-310.pyc
tnia/deconvolution/__pycache__/forward.cpython-312.pyc
tnia/deconvolution/__pycache__/forward.cpython-39.pyc
tnia/deconvolution/__pycache__/gaussian_psf.cpython-310.pyc
tnia/deconvolution/__pycache__/gaussian_psf.cpython-312.pyc
tnia/deconvolution/__pycache__/gaussian_psf.cpython-39.pyc
tnia/deconvolution/__pycache__/pad.cpython-310.pyc
tnia/deconvolution/__pycache__/pad.cpython-312.pyc
tnia/deconvolution/__pycache__/pad.cpython-39.pyc
tnia_python-0.1.27.dist-info/licenses/LICENSE
tnia_python-0.1.27.dist-info/METADATA
tnia_python-0.1.27.dist-info/WHEEL
tnia_python-0.1.27.dist-info/top_level.txt
tnia_python-0.1.27.dist-info/RECORD
