Metadata-Version: 2.4
Name: tnia-python
Version: 0.1.27
Summary: A collection of utilities
Home-page: http://github.com/tnia/tnia-python
Author: Brian Northan
Author-email: bnorthan@gmail.com
License: MIT
License-File: LICENSE
Requires-Dist: albumentations
Requires-Dist: matplotlib
Requires-Dist: scipy
Requires-Dist: tifffile
Requires-Dist: raster-geometry
Dynamic: license-file
